aws_auth_utils/__init__.py
aws_auth_utils/aws_auth.py
aws_auth_utils-1.1.0.dist-info/METADATA
aws_auth_utils-1.1.0.dist-info/WHEEL
aws_auth_utils-1.1.0.dist-info/entry_points.txt
aws_auth_utils-1.1.0.dist-info/licenses/LICENSE
aws_auth_utils-1.1.0.dist-info/RECORD
